setup.py
distributionsuda/Binomialdistribution.py
distributionsuda/Gaussiandistribution.py
distributionsuda/Generaldistribution.py
distributionsuda/__init__.py
distributionsuda.egg-info/PKG-INFO
distributionsuda.egg-info/SOURCES.txt
distributionsuda.egg-info/dependency_links.txt
distributionsuda.egg-info/not-zip-safe
distributionsuda.egg-info/top_level.txt