Metadata-Version: 1.0
Name: distributionsuda
Version: 0.2
Summary: Gaussian distributions
Home-page: UNKNOWN
Author:  Morhaf Jaela
Author-email: morhaf.jely@gmail.com
License: UNKNOWN
Platform: UNKNOWN
